[{"__type__":"cc.Prefab","_name":"damageArea","data":{"__id__":1}},{"__type__":"cc.Node","_name":"damageArea","_components":[{"__type__":"cc.RigidBody","node":{"__id__":1},"_type":1,"_allowSleep":false,"_fixedRotation":true,"enabledContactListener":true},{"__type__":"cc.PhysicsBoxCollider","node":{"__id__":1},"_offset":{"__type__":"cc.Vec2","y":-5},"_size":{"__type__":"cc.Size","width":200,"height":280}},{"__type__":"ade0b/k/E1IIogS+TOKQsLh","node":{"__id__":1}}],"_prefab":{"__type__":"cc.PrefabInfo","root":{"__id__":1},"asset":{"__uuid__":"d9r7lQwI1C5p7KnXGPenR3"},"fileId":"d0uKf+JDdJ37zKNoKKSFpM"},"_trs":{"__type__":"TypedArray","ctor":"Float64Array","array":[0,0,0,0,0,0,1,0.7,0.7,1]},"_groupIndex":5,"groupIndex":5}]